{
    "PON": [
        { 
            "nazwa": "InfLab2P", 
            "godziny": "9:00 AM - 5:00 PM" 
        },
        { 
            "nazwa": "InfLab2P", 
            "godziny": "10:00 AM - 6:00 PM" 
        },
        { 
            "nazwa": "InfLab2P", 
            "godziny": "11:00 AM - 7:00 PM" 
        }
      ],

      "WT": [
        { 
            "nazwa": "InfLab2WT", 
            "godziny": "9:00 AM - 5:00 PM" 
        },
        { 
            "nazwa": "InfLab2WT", 
            "godziny": "10:00 AM - 6:00 PM" 
        },
        { 
            "nazwa": "InfLab2WT", 
            "godziny": "11:00 AM - 7:00 PM" 
        }
      ],

      "SR": [
        { 
            "nazwa": "InfLab2SR", 
            "godziny": "9:00 AM - 5:00 PM" 
        },
        { 
            "nazwa": "InfLab2SR", 
            "godziny": "10:00 AM - 6:00 PM" 
        },
        { 
            "nazwa": "InfLab2SR", 
            "godziny": "11:00 AM - 7:00 PM" 
        }
      ],

      "CZW": [
        { 
            "nazwa": "InfLab2CZW", 
            "godziny": "9:00 AM - 5:00 PM" 
        },
        { 
            "nazwa": "InfLab2CZW", 
            "godziny": "10:00 AM - 6:00 PM" 
        },
        { 
            "nazwa": "InfLab2CZW", 
            "godziny": "11:00 AM - 7:00 PM" 
        }
      ],
      
      "PT": [
        { 
            "nazwa": "InfLab2PT", 
            "godziny": "9:00 AM - 5:00 PM" 
        },
        { 
            "nazwa": "InfLab2PT", 
            "godziny": "10:00 AM - 6:00 PM" 
        },
        { 
            "nazwa": "InfLab2PT", 
            "godziny": "11:00 AM - 7:00 PM" 
        }
      ]  
}